palettesnap/PaletteSnap.py
palettesnap/__init__.py
palettesnap/background.py
palettesnap/cache.py
palettesnap/cli.py
palettesnap/colorClass.py
palettesnap/colorOptimize.py
palettesnap/console.py
palettesnap/outdatedCheck.py
palettesnap/preview.py
palettesnap/refresh.py
palettesnap/setup.py
palettesnap/templating.py
palettesnap/wallpaper.py
palettesnap-1.3.0.dist-info/METADATA
palettesnap-1.3.0.dist-info/WHEEL
palettesnap-1.3.0.dist-info/entry_points.txt
palettesnap-1.3.0.dist-info/RECORD
