Metadata-Version: 2.1
Name: palettesnap
Version: 1.3.0
Summary: A color palette generator
Home-page: https://github.com/EmperorEntropy/PaletteSnap
License: MIT
Author: EmperorEntropy
Requires-Python: >=3.12,<3.13
Classifier: License :: OSI Approved :: MIT License
Classifier: Programming Language :: Python :: 3
Classifier: Programming Language :: Python :: 3.12
Requires-Dist: colour-science (>=0.4.4,<0.5.0)
Requires-Dist: kmedoids (>=0.5.1,<0.6.0)
Requires-Dist: matplotlib (>=3.9.0,<4.0.0)
Requires-Dist: psutil (>=6.0.0,<7.0.0)
Requires-Dist: pykdtree (>=1.3.12,<2.0.0)
Requires-Dist: pymixbox (>=2.0.0,<3.0.0)
Requires-Dist: requests (>=2.32.3,<3.0.0)
Requires-Dist: rich (>=13.7.1,<14.0.0)
Requires-Dist: scikit-learn (>=1.5.1,<2.0.0)
Requires-Dist: toml (>=0.10.2,<0.11.0)
Requires-Dist: typer (>=0.21.0,<0.22.0)
Project-URL: Repository, https://github.com/EmperorEntropy/PaletteSnap
